{
"meta":{"test_sets":[],"test_metrics":[],"learn_metrics":[{"best_value":"Min","name":"MultiClass"}],"launch_mode":"Train","parameters":"","iteration_count":500,"learn_sets":["learn"],"name":"experiment"},
"iterations":[
{"learn":[1.048045395],"iteration":0,"passed_time":0.07971491415,"remaining_time":39.77774216},
{"learn":[1.006654684],"iteration":1,"passed_time":0.09396783077,"remaining_time":23.39798986},
{"learn":[0.9696074024],"iteration":2,"passed_time":0.1001066201,"remaining_time":16.58433007},
{"learn":[0.9323068956],"iteration":3,"passed_time":0.1204779707,"remaining_time":14.93926837},
{"learn":[0.8993172789],"iteration":4,"passed_time":0.1445716548,"remaining_time":14.31259383},
{"learn":[0.8710561451],"iteration":5,"passed_time":0.1621236674,"remaining_time":13.34818195},
{"learn":[0.8429409149],"iteration":6,"passed_time":0.185917317,"remaining_time":13.09389104},
{"learn":[0.8164626265],"iteration":7,"passed_time":0.2102226827,"remaining_time":12.92869499},
{"learn":[0.7928423379],"iteration":8,"passed_time":0.2295333763,"remaining_time":12.52232086},
{"learn":[0.7715920095],"iteration":9,"passed_time":0.241373228,"remaining_time":11.82728817},
{"learn":[0.753097318],"iteration":10,"passed_time":0.251793338,"remaining_time":11.19335839},
{"learn":[0.7296040733],"iteration":11,"passed_time":0.2803944919,"remaining_time":11.40270934},
{"learn":[0.7081120297],"iteration":12,"passed_time":0.3100196271,"remaining_time":11.61381218},
{"learn":[0.6888823003],"iteration":13,"passed_time":0.3350225493,"remaining_time":11.6300685},
{"learn":[0.6688048647],"iteration":14,"passed_time":0.3654878642,"remaining_time":11.81744094},
{"learn":[0.6493310132],"iteration":15,"passed_time":0.3928433738,"remaining_time":11.88351206},
{"learn":[0.6323407844],"iteration":16,"passed_time":0.4207419923,"remaining_time":11.95402249},
{"learn":[0.6159782845],"iteration":17,"passed_time":0.4476247756,"remaining_time":11.98639677},
{"learn":[0.6012359816],"iteration":18,"passed_time":0.4760887703,"remaining_time":12.05256308},
{"learn":[0.5887064947],"iteration":19,"passed_time":0.5130159837,"remaining_time":12.31238361},
{"learn":[0.5763909144],"iteration":20,"passed_time":0.544698941,"remaining_time":12.42432346},
{"learn":[0.5643059896],"iteration":21,"passed_time":0.5786996726,"remaining_time":12.57356561},
{"learn":[0.5523403776],"iteration":22,"passed_time":0.6122371413,"remaining_time":12.69726593},
{"learn":[0.5410487543],"iteration":23,"passed_time":0.6489538283,"remaining_time":12.87091759},
{"learn":[0.5308919612],"iteration":24,"passed_time":0.6882796049,"remaining_time":13.07731249},
{"learn":[0.523962254],"iteration":25,"passed_time":0.7244460036,"remaining_time":13.20720791},
{"learn":[0.5139320876],"iteration":26,"passed_time":0.7628705829,"remaining_time":13.36436243},
{"learn":[0.504044127],"iteration":27,"passed_time":0.8019669152,"remaining_time":13.51887086},
{"learn":[0.4957328004],"iteration":28,"passed_time":0.8420238115,"remaining_time":13.67562811},
{"learn":[0.4876282713],"iteration":29,"passed_time":0.8819734871,"remaining_time":13.81758463},
{"learn":[0.480483985],"iteration":30,"passed_time":0.9184187563,"remaining_time":13.89478699},
{"learn":[0.4741868201],"iteration":31,"passed_time":0.9509081533,"remaining_time":13.90703174},
{"learn":[0.4670301046],"iteration":32,"passed_time":0.9936635959,"remaining_time":14.06184543},
{"learn":[0.4602023564],"iteration":33,"passed_time":1.041316159,"remaining_time":14.27215677},
{"learn":[0.4541221388],"iteration":34,"passed_time":1.089333395,"remaining_time":14.47257225},
{"learn":[0.4486328342],"iteration":35,"passed_time":1.139384483,"remaining_time":14.6854},
{"learn":[0.4429236715],"iteration":36,"passed_time":1.185558087,"remaining_time":14.83549714},
{"learn":[0.4375423417],"iteration":37,"passed_time":1.221437068,"remaining_time":14.85010329},
{"learn":[0.4322082904],"iteration":38,"passed_time":1.253527378,"remaining_time":14.81733644},
{"learn":[0.4276863961],"iteration":39,"passed_time":1.294369209,"remaining_time":14.8852459},
{"learn":[0.4233090727],"iteration":40,"passed_time":1.341522503,"remaining_time":15.01850803},
{"learn":[0.4182671465],"iteration":41,"passed_time":1.38676492,"remaining_time":15.12234127},
{"learn":[0.4140604394],"iteration":42,"passed_time":1.426890827,"remaining_time":15.16486298},
{"learn":[0.4096103181],"iteration":43,"passed_time":1.462446275,"remaining_time":15.15626139},
{"learn":[0.4062083246],"iteration":44,"passed_time":1.500137167,"remaining_time":15.16805357},
{"learn":[0.4023316373],"iteration":45,"passed_time":1.5376562,"remaining_time":15.17599814},
{"learn":[0.3989410164],"iteration":46,"passed_time":1.572449347,"remaining_time":15.1557352},
{"learn":[0.3956610345],"iteration":47,"passed_time":1.605569067,"remaining_time":15.11910872},
{"learn":[0.3927442513],"iteration":48,"passed_time":1.640962405,"remaining_time":15.10355193},
{"learn":[0.3894634366],"iteration":49,"passed_time":1.674843753,"remaining_time":15.07359378},
{"learn":[0.3869178277],"iteration":50,"passed_time":1.708236668,"remaining_time":15.03918165},
{"learn":[0.3847486774],"iteration":51,"passed_time":1.749628619,"remaining_time":15.07372349},
{"learn":[0.381757576],"iteration":52,"passed_time":1.784607807,"remaining_time":15.0513149},
{"learn":[0.3787631121],"iteration":53,"passed_time":1.818417862,"remaining_time":15.01878456},
{"learn":[0.376863877],"iteration":54,"passed_time":1.848197184,"remaining_time":14.9535954},
{"learn":[0.3742398637],"iteration":55,"passed_time":1.889048163,"remaining_time":14.9774533},
{"learn":[0.372214224],"iteration":56,"passed_time":1.931373486,"remaining_time":15.0104992},
{"learn":[0.3700439158],"iteration":57,"passed_time":1.967408345,"remaining_time":14.99300842},
{"learn":[0.3679120168],"iteration":58,"passed_time":2.000755698,"remaining_time":14.95480107},
{"learn":[0.36610373],"iteration":59,"passed_time":2.03674735,"remaining_time":14.93614723},
{"learn":[0.3638945199],"iteration":60,"passed_time":2.070388406,"remaining_time":14.90000836},
{"learn":[0.3620540376],"iteration":61,"passed_time":2.104769747,"remaining_time":14.86917982},
{"learn":[0.3597600948],"iteration":62,"passed_time":2.139308525,"remaining_time":14.83933056},
{"learn":[0.3578323855],"iteration":63,"passed_time":2.172336184,"remaining_time":14.79904025},
{"learn":[0.3562806093],"iteration":64,"passed_time":2.206205194,"remaining_time":14.76460399},
{"learn":[0.3549937414],"iteration":65,"passed_time":2.235534548,"remaining_time":14.70033324},
{"learn":[0.3538133992],"iteration":66,"passed_time":2.26885497,"remaining_time":14.66289854},
{"learn":[0.3520460931],"iteration":67,"passed_time":2.305429464,"remaining_time":14.64625777},
{"learn":[0.3505857607],"iteration":68,"passed_time":2.344610885,"remaining_time":14.64532306},
{"learn":[0.3496408824],"iteration":69,"passed_time":2.37717035,"remaining_time":14.60261786},
{"learn":[0.3483123571],"iteration":70,"passed_time":2.408465694,"remaining_time":14.55256032},
{"learn":[0.3472502742],"iteration":71,"passed_time":2.443146376,"remaining_time":14.5231479},
{"learn":[0.3460607108],"iteration":72,"passed_time":2.47402841,"remaining_time":14.47137166},
{"learn":[0.3450383584],"iteration":73,"passed_time":2.50520296,"remaining_time":14.42184407},
{"learn":[0.3440298561],"iteration":74,"passed_time":2.539018867,"remaining_time":14.38777358},
{"learn":[0.3431954174],"iteration":75,"passed_time":2.57018822,"remaining_time":14.33894481},
{"learn":[0.3425554971],"iteration":76,"passed_time":2.601328647,"remaining_time":14.29041581},
{"learn":[0.341225348],"iteration":77,"passed_time":2.631760052,"remaining_time":14.23849669},
{"learn":[0.3403364984],"iteration":78,"passed_time":2.662487925,"remaining_time":14.18870147},
{"learn":[0.3395082752],"iteration":79,"passed_time":2.693923274,"remaining_time":14.14309719},
{"learn":[0.3384364519],"iteration":80,"passed_time":2.747343367,"remaining_time":14.21156631},
{"learn":[0.3375957994],"iteration":81,"passed_time":2.784994128,"remaining_time":14.19667738},
{"learn":[0.336470396],"iteration":82,"passed_time":2.814514208,"remaining_time":14.14039066},
{"learn":[0.3354428141],"iteration":83,"passed_time":2.846912605,"remaining_time":14.09899576},
{"learn":[0.3344215085],"iteration":84,"passed_time":2.87659604,"remaining_time":14.04455714},
{"learn":[0.3338930138],"iteration":85,"passed_time":2.906076609,"remaining_time":13.98971763},
{"learn":[0.3333023216],"iteration":86,"passed_time":2.938088155,"remaining_time":13.94747595},
{"learn":[0.3324091119],"iteration":87,"passed_time":2.963216757,"remaining_time":13.87324209},
{"learn":[0.3315950257],"iteration":88,"passed_time":2.99273314,"remaining_time":13.82037439},
{"learn":[0.3311001731],"iteration":89,"passed_time":3.024110467,"remaining_time":13.77650324},
{"learn":[0.3305543763],"iteration":90,"passed_time":3.054086905,"remaining_time":13.72661038},
{"learn":[0.3300515514],"iteration":91,"passed_time":3.084831911,"remaining_time":13.68055891},
{"learn":[0.3297101718],"iteration":92,"passed_time":3.11735237,"remaining_time":13.64260661},
{"learn":[0.3291503993],"iteration":93,"passed_time":3.143057869,"remaining_time":13.57533505},
{"learn":[0.328528201],"iteration":94,"passed_time":3.172225618,"remaining_time":13.52369869},
{"learn":[0.3278410915],"iteration":95,"passed_time":3.198043539,"remaining_time":13.45843323},
{"learn":[0.3269938068],"iteration":96,"passed_time":3.228915676,"remaining_time":13.41497956},
{"learn":[0.3265700269],"iteration":97,"passed_time":3.259022741,"remaining_time":13.36864431},
{"learn":[0.3259858591],"iteration":98,"passed_time":3.284917957,"remaining_time":13.30557678},
{"learn":[0.3254290779],"iteration":99,"passed_time":3.314528602,"remaining_time":13.25811441},
{"learn":[0.3248353753],"iteration":100,"passed_time":3.34388902,"remaining_time":13.21001702},
{"learn":[0.3243289301],"iteration":101,"passed_time":3.376157532,"remaining_time":13.17363429},
{"learn":[0.3238267614],"iteration":102,"passed_time":3.408595736,"remaining_time":13.13798551},
{"learn":[0.3233631976],"iteration":103,"passed_time":3.437192501,"remaining_time":13.08777145},
{"learn":[0.3231304475],"iteration":104,"passed_time":3.467191716,"remaining_time":13.04324503},
{"learn":[0.3228224538],"iteration":105,"passed_time":3.49619628,"remaining_time":12.99529561},
{"learn":[0.3222875294],"iteration":106,"passed_time":3.525694502,"remaining_time":12.94951345},
{"learn":[0.3219321138],"iteration":107,"passed_time":3.557188052,"remaining_time":12.91127515},
{"learn":[0.321614566],"iteration":108,"passed_time":3.588238076,"remaining_time":12.87156961},
{"learn":[0.32141601],"iteration":109,"passed_time":3.619592658,"remaining_time":12.83310124},
{"learn":[0.3212332115],"iteration":110,"passed_time":3.644503213,"remaining_time":12.77217793},
{"learn":[0.3207775873],"iteration":111,"passed_time":3.671947297,"remaining_time":12.72067456},
{"learn":[0.3203683653],"iteration":112,"passed_time":3.696657221,"remaining_time":12.66023314},
{"learn":[0.3201532147],"iteration":113,"passed_time":3.721198256,"remaining_time":12.59984673},
{"learn":[0.3197990603],"iteration":114,"passed_time":3.752231982,"remaining_time":12.56182011},
{"learn":[0.3196172655],"iteration":115,"passed_time":3.785649919,"remaining_time":12.53180663},
{"learn":[0.3193590483],"iteration":116,"passed_time":3.816485974,"remaining_time":12.49328315},
{"learn":[0.318764178],"iteration":117,"passed_time":3.845774995,"remaining_time":12.44988176},
{"learn":[0.318436005],"iteration":118,"passed_time":3.874635356,"remaining_time":12.40534513},
{"learn":[0.3182027391],"iteration":119,"passed_time":3.906604401,"remaining_time":12.37091394},
{"learn":[0.3178338618],"iteration":120,"passed_time":3.933345215,"remaining_time":12.32014741},
{"learn":[0.3175918398],"iteration":121,"passed_time":3.964577191,"remaining_time":12.28368999},
{"learn":[0.3173061638],"iteration":122,"passed_time":4.000707659,"remaining_time":12.26233161},
{"learn":[0.3170595373],"iteration":123,"passed_time":4.040385356,"remaining_time":12.25149108},
{"learn":[0.3169785918],"iteration":124,"passed_time":4.079885539,"remaining_time":12.23965662},
{"learn":[0.3167425067],"iteration":125,"passed_time":4.123251858,"remaining_time":12.23885869},
{"learn":[0.3164574742],"iteration":126,"passed_time":4.15810794,"remaining_time":12.21239576},
{"learn":[0.316314063],"iteration":127,"passed_time":4.195841617,"remaining_time":12.1941647},
{"learn":[0.3160314003],"iteration":128,"passed_time":4.227604172,"remaining_time":12.15845851},
{"learn":[0.3157994968],"iteration":129,"passed_time":4.264504655,"remaining_time":12.13743633},
{"learn":[0.3155318027],"iteration":130,"passed_time":4.301890817,"remaining_time":12.11753978},
{"learn":[0.3153551695],"iteration":131,"passed_time":4.33672579,"remaining_time":12.09026584},
{"learn":[0.3149844064],"iteration":132,"passed_time":4.382370207,"remaining_time":12.09270576},
{"learn":[0.3147586945],"iteration":133,"passed_time":4.419875052,"remaining_time":12.07219604},
{"learn":[0.3144576051],"iteration":134,"passed_time":4.46040038,"remaining_time":12.05960103},
{"learn":[0.3142592455],"iteration":135,"passed_time":4.497877892,"remaining_time":12.03843789},
{"learn":[0.3140999065],"iteration":136,"passed_time":4.538060859,"remaining_time":12.02420505},
{"learn":[0.3139167536],"iteration":137,"passed_time":4.569047477,"remaining_time":11.98547237},
{"learn":[0.3134352033],"iteration":138,"passed_time":4.604138095,"remaining_time":11.95750973},
{"learn":[0.3132123306],"iteration":139,"passed_time":4.642357943,"remaining_time":11.93749185},
{"learn":[0.313009768],"iteration":140,"passed_time":4.681452879,"remaining_time":11.91944386},
{"learn":[0.3129763363],"iteration":141,"passed_time":4.716853173,"remaining_time":11.89178476},
{"learn":[0.3126852556],"iteration":142,"passed_time":4.754086263,"remaining_time":11.86859298},
{"learn":[0.3124408464],"iteration":143,"passed_time":4.786803546,"remaining_time":11.8340421},
{"learn":[0.3122302396],"iteration":144,"passed_time":4.825429525,"remaining_time":11.81398263},
{"learn":[0.311887865],"iteration":145,"passed_time":4.862486754,"remaining_time":11.78986514},
{"learn":[0.3116042892],"iteration":146,"passed_time":4.898851779,"remaining_time":11.76390937},
{"learn":[0.3113313272],"iteration":147,"passed_time":4.931319544,"remaining_time":11.72854378},
{"learn":[0.3111272794],"iteration":148,"passed_time":4.967453542,"remaining_time":11.70185365},
{"learn":[0.3109663643],"iteration":149,"passed_time":4.991491146,"remaining_time":11.64681267},
{"learn":[0.3104666245],"iteration":150,"passed_time":5.023593612,"remaining_time":11.61082232},
{"learn":[0.3103081802],"iteration":151,"passed_time":5.055021393,"remaining_time":11.57333845},
{"learn":[0.3100047862],"iteration":152,"passed_time":5.084638281,"remaining_time":11.53182669},
{"learn":[0.3097698771],"iteration":153,"passed_time":5.110663829,"remaining_time":11.48240055},
{"learn":[0.3095923838],"iteration":154,"passed_time":5.142394059,"remaining_time":11.44597387},
{"learn":[0.3095146485],"iteration":155,"passed_time":5.175615922,"remaining_time":11.41289665},
{"learn":[0.3093727661],"iteration":156,"passed_time":5.216654532,"remaining_time":11.39689493},
{"learn":[0.309233659],"iteration":157,"passed_time":5.256073975,"remaining_time":11.37707152},
{"learn":[0.309058269],"iteration":158,"passed_time":5.292699405,"remaining_time":11.35100941},
{"learn":[0.3087906929],"iteration":159,"passed_time":5.329164914,"remaining_time":11.32447544},
{"learn":[0.3086835159],"iteration":160,"passed_time":5.36651951,"remaining_time":11.29969015},
{"learn":[0.3085393776],"iteration":161,"passed_time":5.401536642,"remaining_time":11.26987275},
{"learn":[0.3082513343],"iteration":162,"passed_time":5.43406945,"remaining_time":11.23485524},
{"learn":[0.307947012],"iteration":163,"passed_time":5.463633072,"remaining_time":11.19378483},
{"learn":[0.3079350087],"iteration":164,"passed_time":5.4744023,"remaining_time":11.11469558},
{"learn":[0.3074766834],"iteration":165,"passed_time":5.501731836,"remaining_time":11.0697496},
{"learn":[0.3073435185],"iteration":166,"passed_time":5.526657947,"remaining_time":11.02022213},
{"learn":[0.30717265],"iteration":167,"passed_time":5.554368304,"remaining_time":10.97648974},
{"learn":[0.307001991],"iteration":168,"passed_time":5.578787654,"remaining_time":10.92650126},
{"learn":[0.3069381764],"iteration":169,"passed_time":5.60405312,"remaining_time":10.87845606},
{"learn":[0.3069017062],"iteration":170,"passed_time":5.629016145,"remaining_time":10.83009539},
{"learn":[0.3068432967],"iteration":171,"passed_time":5.654724616,"remaining_time":10.78342834},
{"learn":[0.3066573685],"iteration":172,"passed_time":5.680253723,"remaining_time":10.73666455},
{"learn":[0.3064330289],"iteration":173,"passed_time":5.707242796,"remaining_time":10.69288018},
{"learn":[0.306291013],"iteration":174,"passed_time":5.733436747,"remaining_time":10.6478111},
{"learn":[0.3059130456],"iteration":175,"passed_time":5.761928601,"remaining_time":10.60718674},
{"learn":[0.305718684],"iteration":176,"passed_time":5.792163003,"remaining_time":10.56987938},
{"learn":[0.3055345346],"iteration":177,"passed_time":5.818796158,"remaining_time":10.52613687},
{"learn":[0.3051106425],"iteration":178,"passed_time":5.845989597,"remaining_time":10.48359028},
{"learn":[0.3049422417],"iteration":179,"passed_time":5.870210054,"remaining_time":10.43592898},
{"learn":[0.3047062085],"iteration":180,"passed_time":5.895909658,"remaining_time":10.3911336},
{"learn":[0.3046410288],"iteration":181,"passed_time":5.930109961,"remaining_time":10.36140092},
{"learn":[0.3045243453],"iteration":182,"passed_time":5.966128224,"remaining_time":10.33476856},
{"learn":[0.3043786402],"iteration":183,"passed_time":6.000862669,"remaining_time":10.30582937},
{"learn":[0.3040869481],"iteration":184,"passed_time":6.040379037,"remaining_time":10.28496971},
{"learn":[0.3039927366],"iteration":185,"passed_time":6.082360825,"remaining_time":10.2680715},
{"learn":[0.3036933666],"iteration":186,"passed_time":6.116212272,"remaining_time":10.23729648},
{"learn":[0.3034251118],"iteration":187,"passed_time":6.152516689,"remaining_time":10.21055961},
{"learn":[0.3031938524],"iteration":188,"passed_time":6.190996205,"remaining_time":10.18730063},
{"learn":[0.3030222185],"iteration":189,"passed_time":6.226703766,"remaining_time":10.15935878},
{"learn":[0.3027286914],"iteration":190,"passed_time":6.257260156,"remaining_time":10.12300203},
{"learn":[0.3024786102],"iteration":191,"passed_time":6.290943633,"remaining_time":10.09172208},
{"learn":[0.3023689265],"iteration":192,"passed_time":6.322985219,"remaining_time":10.0578055},
{"learn":[0.3022493721],"iteration":193,"passed_time":6.356242087,"remaining_time":10.02582515},
{"learn":[0.3020960332],"iteration":194,"passed_time":6.389481594,"remaining_time":9.993804544},
{"learn":[0.3019914687],"iteration":195,"passed_time":6.424206974,"remaining_time":9.964076123},
{"learn":[0.3018171548],"iteration":196,"passed_time":6.466865459,"remaining_time":9.94649865},
{"learn":[0.301672362],"iteration":197,"passed_time":6.504372701,"remaining_time":9.920810887},
{"learn":[0.3016011441],"iteration":198,"passed_time":6.546077076,"remaining_time":9.901352762},
{"learn":[0.3014576075],"iteration":199,"passed_time":6.592072334,"remaining_time":9.888108501},
{"learn":[0.3012295393],"iteration":200,"passed_time":6.633116669,"remaining_time":9.867173553},
{"learn":[0.3010439849],"iteration":201,"passed_time":6.67096454,"remaining_time":9.841323926},
{"learn":[0.3008042716],"iteration":202,"passed_time":6.70373842,"remaining_time":9.807932565},
{"learn":[0.3006085223],"iteration":203,"passed_time":6.737611164,"remaining_time":9.776141689},
{"learn":[0.3004046063],"iteration":204,"passed_time":6.767155582,"remaining_time":9.738101935},
{"learn":[0.3002353877],"iteration":205,"passed_time":6.797199065,"remaining_time":9.700856919},
{"learn":[0.3001087792],"iteration":206,"passed_time":6.826430602,"remaining_time":9.662532205},
{"learn":[0.2999152973],"iteration":207,"passed_time":6.858017946,"remaining_time":9.627602117},
{"learn":[0.2998184556],"iteration":208,"passed_time":6.888247613,"remaining_time":9.590813662},
{"learn":[0.2997291341],"iteration":209,"passed_time":6.923168932,"remaining_time":9.56056662},
{"learn":[0.2996275557],"iteration":210,"passed_time":6.964712006,"remaining_time":9.539344881},
{"learn":[0.2993324708],"iteration":211,"passed_time":6.999992703,"remaining_time":9.50942405},
{"learn":[0.2991489207],"iteration":212,"passed_time":7.035145584,"remaining_time":9.47928067},
{"learn":[0.2990816709],"iteration":213,"passed_time":7.070596357,"remaining_time":9.449488589},
{"learn":[0.2990305944],"iteration":214,"passed_time":7.103315199,"remaining_time":9.416022473},
{"learn":[0.2988596817],"iteration":215,"passed_time":7.137552164,"remaining_time":9.384559327},
{"learn":[0.2987226504],"iteration":216,"passed_time":7.175602524,"remaining_time":9.358043844},
{"learn":[0.2985461659],"iteration":217,"passed_time":7.209868963,"remaining_time":9.326527741},
{"learn":[0.2982213746],"iteration":218,"passed_time":7.241814404,"remaining_time":9.292008436},
{"learn":[0.2981049717],"iteration":219,"passed_time":7.279629055,"remaining_time":9.264982434},
{"learn":[0.2980830941],"iteration":220,"passed_time":7.314203522,"remaining_time":9.233768247},
{"learn":[0.2980177325],"iteration":221,"passed_time":7.350770263,"remaining_time":9.205018618},
{"learn":[0.2977023611],"iteration":222,"passed_time":7.377114275,"remaining_time":9.163500692},
{"learn":[0.2976240934],"iteration":223,"passed_time":7.405450043,"remaining_time":9.124572374},
{"learn":[0.2974988907],"iteration":224,"passed_time":7.44175507,"remaining_time":9.095478419},
{"learn":[0.2973662555],"iteration":225,"passed_time":7.478424813,"remaining_time":9.066762826},
{"learn":[0.2971153351],"iteration":226,"passed_time":7.515969369,"remaining_time":9.039029241},
{"learn":[0.2970114471],"iteration":227,"passed_time":7.553846543,"remaining_time":9.011606402},
{"learn":[0.2969009801],"iteration":228,"passed_time":7.585661204,"remaining_time":8.976917844},
{"learn":[0.296784682],"iteration":229,"passed_time":7.619137521,"remaining_time":8.944204916},
{"learn":[0.29659015],"iteration":230,"passed_time":7.650073113,"remaining_time":8.908526698},
{"learn":[0.2964986186],"iteration":231,"passed_time":7.694057677,"remaining_time":8.887963179},
{"learn":[0.2963767087],"iteration":232,"passed_time":7.734135803,"remaining_time":8.862722143},
{"learn":[0.296219647],"iteration":233,"passed_time":7.767497506,"remaining_time":8.829719388},
{"learn":[0.2960542213],"iteration":234,"passed_time":7.801138909,"remaining_time":8.797028982},
{"learn":[0.2959251127],"iteration":235,"passed_time":7.836676937,"remaining_time":8.766452167},
{"learn":[0.2958767511],"iteration":236,"passed_time":7.864146756,"remaining_time":8.726880155},
{"learn":[0.2957091724],"iteration":237,"passed_time":7.89860398,"remaining_time":8.69510186},
{"learn":[0.2954833078],"iteration":238,"passed_time":7.92833394,"remaining_time":8.658138738},
{"learn":[0.2954129339],"iteration":239,"passed_time":7.962343552,"remaining_time":8.625872181},
{"learn":[0.2952660119],"iteration":240,"passed_time":7.994625357,"remaining_time":8.591734305},
{"learn":[0.2952047928],"iteration":241,"passed_time":8.026744074,"remaining_time":8.557437897},
{"learn":[0.2951514375],"iteration":242,"passed_time":8.057327573,"remaining_time":8.521535746},
{"learn":[0.2950597225],"iteration":243,"passed_time":8.084365363,"remaining_time":8.481957102},
{"learn":[0.2950136892],"iteration":244,"passed_time":8.11306934,"remaining_time":8.444215028},
{"learn":[0.2949795681],"iteration":245,"passed_time":8.139985994,"remaining_time":8.404700985},
{"learn":[0.2948106285],"iteration":246,"passed_time":8.166669565,"remaining_time":8.365050202},
{"learn":[0.2947198385],"iteration":247,"passed_time":8.194441871,"remaining_time":8.326610289},
{"learn":[0.2946082649],"iteration":248,"passed_time":8.220718848,"remaining_time":8.286748719},
{"learn":[0.2944258839],"iteration":249,"passed_time":8.246736994,"remaining_time":8.246736994},
{"learn":[0.2943483798],"iteration":250,"passed_time":8.275584638,"remaining_time":8.209643725},
{"learn":[0.2942592778],"iteration":251,"passed_time":8.30330336,"remaining_time":8.171504894},
{"learn":[0.2941116556],"iteration":252,"passed_time":8.32970827,"remaining_time":8.132165781},
{"learn":[0.2939814281],"iteration":253,"passed_time":8.357435884,"remaining_time":8.094209557},
{"learn":[0.2938933133],"iteration":254,"passed_time":8.384780986,"remaining_time":8.055966045},
{"learn":[0.2938398571],"iteration":255,"passed_time":8.415373103,"remaining_time":8.020902489},
{"learn":[0.2937275397],"iteration":256,"passed_time":8.444760859,"remaining_time":7.984734975},
{"learn":[0.293633826],"iteration":257,"passed_time":8.472332966,"remaining_time":7.946916968},
{"learn":[0.2934166245],"iteration":258,"passed_time":8.502513619,"remaining_time":7.911605337},
{"learn":[0.2933712872],"iteration":259,"passed_time":8.53141501,"remaining_time":7.875152317},
{"learn":[0.293224344],"iteration":260,"passed_time":8.5617609,"remaining_time":7.840079905},
{"learn":[0.2930707718],"iteration":261,"passed_time":8.590058812,"remaining_time":7.803183196},
{"learn":[0.2927890673],"iteration":262,"passed_time":8.619601788,"remaining_time":7.767473855},
{"learn":[0.2926974487],"iteration":263,"passed_time":8.650204836,"remaining_time":7.732758868},
{"learn":[0.2926356872],"iteration":264,"passed_time":8.678567342,"remaining_time":7.69608802},
{"learn":[0.2925982011],"iteration":265,"passed_time":8.704495557,"remaining_time":7.657338197},
{"learn":[0.292383878],"iteration":266,"passed_time":8.727541715,"remaining_time":7.616169362},
{"learn":[0.292264521],"iteration":267,"passed_time":8.754162257,"remaining_time":7.578230014},
{"learn":[0.2921621307],"iteration":268,"passed_time":8.779747046,"remaining_time":7.539485381},
{"learn":[0.2919324025],"iteration":269,"passed_time":8.806491935,"remaining_time":7.501826464},
{"learn":[0.2918680002],"iteration":270,"passed_time":8.832494558,"remaining_time":7.463620863},
{"learn":[0.2917851716],"iteration":271,"passed_time":8.855641765,"remaining_time":7.423111479},
{"learn":[0.2917221652],"iteration":272,"passed_time":8.880750033,"remaining_time":7.384359918},
{"learn":[0.2916089169],"iteration":273,"passed_time":8.906982921,"remaining_time":7.346635548},
{"learn":[0.2915164688],"iteration":274,"passed_time":8.933723902,"remaining_time":7.309410465},
{"learn":[0.2913918539],"iteration":275,"passed_time":8.95732324,"remaining_time":7.269711615},
{"learn":[0.2912688052],"iteration":276,"passed_time":8.98395159,"remaining_time":7.232567526},
{"learn":[0.2911218587],"iteration":277,"passed_time":9.009192063,"remaining_time":7.194390784},
{"learn":[0.2909674984],"iteration":278,"passed_time":9.035620051,"remaining_time":7.157247424},
{"learn":[0.2908784373],"iteration":279,"passed_time":9.061325062,"remaining_time":7.119612548},
{"learn":[0.2906402401],"iteration":280,"passed_time":9.087677347,"remaining_time":7.082567043},
{"learn":[0.2905632371],"iteration":281,"passed_time":9.11156458,"remaining_time":7.043691767},
{"learn":[0.2903846884],"iteration":282,"passed_time":9.137637114,"remaining_time":7.00659807},
{"learn":[0.2903008643],"iteration":283,"passed_time":9.162962392,"remaining_time":6.96901365},
{"learn":[0.2901440322],"iteration":284,"passed_time":9.188536372,"remaining_time":6.931702877},
{"learn":[0.2900775813],"iteration":285,"passed_time":9.215439092,"remaining_time":6.895468412},
{"learn":[0.2900280484],"iteration":286,"passed_time":9.240016073,"remaining_time":6.857572904},
{"learn":[0.2897284931],"iteration":287,"passed_time":9.269714177,"remaining_time":6.823539603},
{"learn":[0.2895907351],"iteration":288,"passed_time":9.292720841,"remaining_time":6.784650856},
{"learn":[0.2894833371],"iteration":289,"passed_time":9.317507107,"remaining_time":6.747160319},
{"learn":[0.2894547224],"iteration":290,"passed_time":9.344205425,"remaining_time":6.711130357},
{"learn":[0.2893309194],"iteration":291,"passed_time":9.369300029,"remaining_time":6.674021938},
{"learn":[0.2892584815],"iteration":292,"passed_time":9.392485284,"remaining_time":6.6356466},
{"learn":[0.2892129131],"iteration":293,"passed_time":9.418498563,"remaining_time":6.599356136},
{"learn":[0.2890660919],"iteration":294,"passed_time":9.443409569,"remaining_time":6.562369361},
{"learn":[0.2889990967],"iteration":295,"passed_time":9.472672609,"remaining_time":6.528463555},
{"learn":[0.2889137296],"iteration":296,"passed_time":9.498820603,"remaining_time":6.492459874},
{"learn":[0.2885777648],"iteration":297,"passed_time":9.52584851,"remaining_time":6.457118789},
{"learn":[0.288425042],"iteration":298,"passed_time":9.5512486,"remaining_time":6.420739026},
{"learn":[0.288298573],"iteration":299,"passed_time":9.577740624,"remaining_time":6.385160416},
{"learn":[0.2882283491],"iteration":300,"passed_time":9.604372453,"remaining_time":6.349734612},
{"learn":[0.2881240099],"iteration":301,"passed_time":9.629190761,"remaining_time":6.313178049},
{"learn":[0.2880049745],"iteration":302,"passed_time":9.654392192,"remaining_time":6.276948059},
{"learn":[0.287904921],"iteration":303,"passed_time":9.682264374,"remaining_time":6.242512557},
{"learn":[0.2877981704],"iteration":304,"passed_time":9.707264267,"remaining_time":6.206283712},
{"learn":[0.2876566236],"iteration":305,"passed_time":9.728150267,"remaining_time":6.167520104},
{"learn":[0.2875393527],"iteration":306,"passed_time":9.758750456,"remaining_time":6.134979928},
{"learn":[0.2873788428],"iteration":307,"passed_time":9.790406549,"remaining_time":6.103110576},
{"learn":[0.2873341568],"iteration":308,"passed_time":9.82284555,"remaining_time":6.071726537},
{"learn":[0.2871972862],"iteration":309,"passed_time":9.856144746,"remaining_time":6.040862909},
{"learn":[0.2870845661],"iteration":310,"passed_time":9.885634828,"remaining_time":6.007668754},
{"learn":[0.2870731904],"iteration":311,"passed_time":9.915242879,"remaining_time":5.974569427},
{"learn":[0.2870427786],"iteration":312,"passed_time":9.942517704,"remaining_time":5.940098436},
{"learn":[0.2869921251],"iteration":313,"passed_time":9.96638553,"remaining_time":5.903655123},
{"learn":[0.2868859665],"iteration":314,"passed_time":9.99353088,"remaining_time":5.869216549},
{"learn":[0.2866902353],"iteration":315,"passed_time":10.01993367,"remaining_time":5.834391756},
{"learn":[0.2865852756],"iteration":316,"passed_time":10.04560256,"remaining_time":5.799196428},
{"learn":[0.2864810811],"iteration":317,"passed_time":10.07169874,"remaining_time":5.764305567},
{"learn":[0.2863396762],"iteration":318,"passed_time":10.09811173,"remaining_time":5.729649603},
{"learn":[0.2861185928],"iteration":319,"passed_time":10.12477941,"remaining_time":5.695188418},
{"learn":[0.2860138388],"iteration":320,"passed_time":10.15166301,"remaining_time":5.660896195},
{"learn":[0.2859209512],"iteration":321,"passed_time":10.17703754,"remaining_time":5.625815781},
{"learn":[0.2858432046],"iteration":322,"passed_time":10.20349414,"remaining_time":5.59138843},
{"learn":[0.2857967292],"iteration":323,"passed_time":10.2297867,"remaining_time":5.556921173},
{"learn":[0.2856427626],"iteration":324,"passed_time":10.25871985,"remaining_time":5.523926071},
{"learn":[0.2854638075],"iteration":325,"passed_time":10.28730164,"remaining_time":5.490768358},
{"learn":[0.2854354531],"iteration":326,"passed_time":10.31510263,"remaining_time":5.457225549},
{"learn":[0.2853232059],"iteration":327,"passed_time":10.34029793,"remaining_time":5.422351352},
{"learn":[0.2851073123],"iteration":328,"passed_time":10.3679848,"remaining_time":5.388831005},
{"learn":[0.2850025271],"iteration":329,"passed_time":10.40092856,"remaining_time":5.358054107},
{"learn":[0.2848337255],"iteration":330,"passed_time":10.43447796,"remaining_time":5.327573339},
{"learn":[0.2847484877],"iteration":331,"passed_time":10.47134573,"remaining_time":5.298753261},
{"learn":[0.2846091804],"iteration":332,"passed_time":10.50672361,"remaining_time":5.269137667},
{"learn":[0.2845374613],"iteration":333,"passed_time":10.53804731,"remaining_time":5.237472615},
{"learn":[0.2845148201],"iteration":334,"passed_time":10.57328706,"remaining_time":5.207738401},
{"learn":[0.2844174415],"iteration":335,"passed_time":10.60655524,"remaining_time":5.177009106},
{"learn":[0.284157077],"iteration":336,"passed_time":10.63723654,"remaining_time":5.14501352},
{"learn":[0.2840771944],"iteration":337,"passed_time":10.66824374,"remaining_time":5.11318191},
{"learn":[0.2838997684],"iteration":338,"passed_time":10.70382156,"remaining_time":5.083525874},
{"learn":[0.2836393551],"iteration":339,"passed_time":10.73889879,"remaining_time":5.053599431},
{"learn":[0.2835790724],"iteration":340,"passed_time":10.77476782,"remaining_time":5.024011975},
{"learn":[0.2834569128],"iteration":341,"passed_time":10.8050796,"remaining_time":4.991820402},
{"learn":[0.2833777691],"iteration":342,"passed_time":10.83532002,"remaining_time":4.959607122},
{"learn":[0.2832555218],"iteration":343,"passed_time":10.86290465,"remaining_time":4.926200946},
{"learn":[0.2831863367],"iteration":344,"passed_time":10.88941267,"remaining_time":4.892344825},
{"learn":[0.283065177],"iteration":345,"passed_time":10.92693599,"remaining_time":4.863433938},
{"learn":[0.2830175216],"iteration":346,"passed_time":10.95485254,"remaining_time":4.830237574},
{"learn":[0.28290728],"iteration":347,"passed_time":10.98885915,"remaining_time":4.799731581},
{"learn":[0.2826730177],"iteration":348,"passed_time":11.02404809,"remaining_time":4.769717082},
{"learn":[0.2825168321],"iteration":349,"passed_time":11.05041421,"remaining_time":4.735891804},
{"learn":[0.2824344483],"iteration":350,"passed_time":11.0806828,"remaining_time":4.703765633},
{"learn":[0.2823874385],"iteration":351,"passed_time":11.10630011,"remaining_time":4.669694364},
{"learn":[0.2822837573],"iteration":352,"passed_time":11.13612536,"remaining_time":4.637423311},
{"learn":[0.2821982241],"iteration":353,"passed_time":11.16397384,"remaining_time":4.604350794},
{"learn":[0.282144137],"iteration":354,"passed_time":11.18873725,"remaining_time":4.570047608},
{"learn":[0.2820485491],"iteration":355,"passed_time":11.21132415,"remaining_time":4.534917632},
{"learn":[0.2818531974],"iteration":356,"passed_time":11.23868265,"remaining_time":4.501769239},
{"learn":[0.2817969509],"iteration":357,"passed_time":11.26466046,"remaining_time":4.468105547},
{"learn":[0.2817352041],"iteration":358,"passed_time":11.28905231,"remaining_time":4.43386177},
{"learn":[0.2816219881],"iteration":359,"passed_time":11.31796483,"remaining_time":4.401430768},
{"learn":[0.2816113305],"iteration":360,"passed_time":11.34641025,"remaining_time":4.368839405},
{"learn":[0.2815316751],"iteration":361,"passed_time":11.37368123,"remaining_time":4.33582323},
{"learn":[0.2814748237],"iteration":362,"passed_time":11.40099159,"remaining_time":4.302853574},
{"learn":[0.2814494715],"iteration":363,"passed_time":11.42951047,"remaining_time":4.270366549},
{"learn":[0.2813379486],"iteration":364,"passed_time":11.45133403,"remaining_time":4.235424914},
{"learn":[0.281231302],"iteration":365,"passed_time":11.47505829,"remaining_time":4.201250848},
{"learn":[0.2811458403],"iteration":366,"passed_time":11.4971017,"remaining_time":4.166524596},
{"learn":[0.2810228836],"iteration":367,"passed_time":11.52136901,"remaining_time":4.132664972},
{"learn":[0.2808337421],"iteration":368,"passed_time":11.54624087,"remaining_time":4.099071962},
{"learn":[0.2807727136],"iteration":369,"passed_time":11.57414812,"remaining_time":4.066592584},
{"learn":[0.2806507835],"iteration":370,"passed_time":11.60195679,"remaining_time":4.034103574},
{"learn":[0.2804906072],"iteration":371,"passed_time":11.62465056,"remaining_time":3.999879762},
{"learn":[0.2804011415],"iteration":372,"passed_time":11.65148435,"remaining_time":3.96712738},
{"learn":[0.2803679753],"iteration":373,"passed_time":11.6783219,"remaining_time":3.934407914},
{"learn":[0.2802523706],"iteration":374,"passed_time":11.70130356,"remaining_time":3.90043452},
{"learn":[0.2800805208],"iteration":375,"passed_time":11.72851136,"remaining_time":3.867913321},
{"learn":[0.2799938218],"iteration":376,"passed_time":11.75657433,"remaining_time":3.835699317},
{"learn":[0.2799133751],"iteration":377,"passed_time":11.78442165,"remaining_time":3.803437674},
{"learn":[0.2797541589],"iteration":378,"passed_time":11.81281464,"remaining_time":3.77137354},
{"learn":[0.279566318],"iteration":379,"passed_time":11.83989866,"remaining_time":3.738915366},
{"learn":[0.2795253503],"iteration":380,"passed_time":11.87005258,"remaining_time":3.707444244},
{"learn":[0.2793859025],"iteration":381,"passed_time":11.89942937,"remaining_time":3.675739964},
{"learn":[0.2793614528],"iteration":382,"passed_time":11.92979576,"remaining_time":3.644350141},
{"learn":[0.279283539],"iteration":383,"passed_time":11.96614689,"remaining_time":3.614773539},
{"learn":[0.2792374112],"iteration":384,"passed_time":11.99771048,"remaining_time":3.583731703},
{"learn":[0.2791946064],"iteration":385,"passed_time":12.03586365,"remaining_time":3.554633306},
{"learn":[0.2791054515],"iteration":386,"passed_time":12.06450256,"remaining_time":3.522710051},
{"learn":[0.278973664],"iteration":387,"passed_time":12.09693361,"remaining_time":3.491898361},
{"learn":[0.2788851858],"iteration":388,"passed_time":12.12871953,"remaining_time":3.460894263},
{"learn":[0.2787968954],"iteration":389,"passed_time":12.16699241,"remaining_time":3.431715809},
{"learn":[0.2787329052],"iteration":390,"passed_time":12.19797588,"remaining_time":3.400458749},
{"learn":[0.2786272517],"iteration":391,"passed_time":12.23207566,"remaining_time":3.370061661},
{"learn":[0.2785274844],"iteration":392,"passed_time":12.2693283,"remaining_time":3.340504143},
{"learn":[0.2784565331],"iteration":393,"passed_time":12.30481955,"remaining_time":3.310433686},
{"learn":[0.2782563545],"iteration":394,"passed_time":12.34039264,"remaining_time":3.280357536},
{"learn":[0.2782145316],"iteration":395,"passed_time":12.37666424,"remaining_time":3.250437074},
{"learn":[0.2779405897],"iteration":396,"passed_time":12.41081685,"remaining_time":3.219934849},
{"learn":[0.2778547816],"iteration":397,"passed_time":12.44954644,"remaining_time":3.190587279},
{"learn":[0.2778253871],"iteration":398,"passed_time":12.48237621,"remaining_time":3.159699242},
{"learn":[0.277803896],"iteration":399,"passed_time":12.51903284,"remaining_time":3.12975821},
{"learn":[0.2777425315],"iteration":400,"passed_time":12.55588707,"remaining_time":3.099832468},
{"learn":[0.2777089288],"iteration":401,"passed_time":12.59082084,"remaining_time":3.069404085},
{"learn":[0.2775367016],"iteration":402,"passed_time":12.62018375,"remaining_time":3.037612466},
{"learn":[0.2774105111],"iteration":403,"passed_time":12.65124105,"remaining_time":3.006235497},
{"learn":[0.2773809492],"iteration":404,"passed_time":12.68268052,"remaining_time":2.974949752},
{"learn":[0.2772383143],"iteration":405,"passed_time":12.71759795,"remaining_time":2.944468492},
{"learn":[0.277203568],"iteration":406,"passed_time":12.7509049,"remaining_time":2.913597435},
{"learn":[0.2771249999],"iteration":407,"passed_time":12.78596754,"remaining_time":2.883110329},
{"learn":[0.2769994762],"iteration":408,"passed_time":12.82335674,"remaining_time":2.853118493},
{"learn":[0.2769582133],"iteration":409,"passed_time":12.85909443,"remaining_time":2.822728045},
{"learn":[0.2768198926],"iteration":410,"passed_time":12.89008048,"remaining_time":2.791282635},
{"learn":[0.2767477081],"iteration":411,"passed_time":12.92086647,"remaining_time":2.759796722},
{"learn":[0.2766823369],"iteration":412,"passed_time":12.95287039,"remaining_time":2.728570759},
{"learn":[0.2766335972],"iteration":413,"passed_time":12.98593676,"remaining_time":2.697561743},
{"learn":[0.2766069568],"iteration":414,"passed_time":13.01834313,"remaining_time":2.66640763},
{"learn":[0.2765167547],"iteration":415,"passed_time":13.05087109,"remaining_time":2.635272046},
{"learn":[0.2764191368],"iteration":416,"passed_time":13.08241566,"remaining_time":2.603934052},
{"learn":[0.2763170563],"iteration":417,"passed_time":13.1097535,"remaining_time":2.571769825},
{"learn":[0.2762048156],"iteration":418,"passed_time":13.13892263,"remaining_time":2.539982657},
{"learn":[0.2761507957],"iteration":419,"passed_time":13.16684585,"remaining_time":2.507970639},
{"learn":[0.2760850223],"iteration":420,"passed_time":13.19459841,"remaining_time":2.475946019},
{"learn":[0.2759994914],"iteration":421,"passed_time":13.22793612,"remaining_time":2.444973974},
{"learn":[0.2758887159],"iteration":422,"passed_time":13.25929663,"remaining_time":2.413630829},
{"learn":[0.2757424177],"iteration":423,"passed_time":13.29365418,"remaining_time":2.382824806},
{"learn":[0.2756538139],"iteration":424,"passed_time":13.32788456,"remaining_time":2.351979628},
{"learn":[0.2755738689],"iteration":425,"passed_time":13.36243126,"remaining_time":2.321173506},
{"learn":[0.2754930252],"iteration":426,"passed_time":13.39136365,"remaining_time":2.289390039},
{"learn":[0.2754427097],"iteration":427,"passed_time":13.42388163,"remaining_time":2.258223078},
{"learn":[0.2753798223],"iteration":428,"passed_time":13.45723799,"remaining_time":2.227188572},
{"learn":[0.275283397],"iteration":429,"passed_time":13.48714037,"remaining_time":2.19558099},
{"learn":[0.2752415897],"iteration":430,"passed_time":13.5142845,"remaining_time":2.163539746},
{"learn":[0.2751480953],"iteration":431,"passed_time":13.54041141,"remaining_time":2.131361056},
{"learn":[0.2750246442],"iteration":432,"passed_time":13.56453087,"remaining_time":2.098899696},
{"learn":[0.2749099102],"iteration":433,"passed_time":13.5912642,"remaining_time":2.066874279},
{"learn":[0.2747753637],"iteration":434,"passed_time":13.62157085,"remaining_time":2.035407138},
{"learn":[0.2746961642],"iteration":435,"passed_time":13.64743443,"remaining_time":2.003293127},
{"learn":[0.2746376334],"iteration":436,"passed_time":13.67192538,"remaining_time":1.971009838},
{"learn":[0.2744992022],"iteration":437,"passed_time":13.70137942,"remaining_time":1.939464667},
{"learn":[0.2744635631],"iteration":438,"passed_time":13.73787401,"remaining_time":1.908907323},
{"learn":[0.2743776171],"iteration":439,"passed_time":13.77682738,"remaining_time":1.87865828},
{"learn":[0.2743238443],"iteration":440,"passed_time":13.80928609,"remaining_time":1.84750086},
{"learn":[0.2741499947],"iteration":441,"passed_time":13.84639406,"remaining_time":1.816947637},
{"learn":[0.274107923],"iteration":442,"passed_time":13.8773668,"remaining_time":1.785575413},
{"learn":[0.2740580804],"iteration":443,"passed_time":13.90650496,"remaining_time":1.753973598},
{"learn":[0.2739970756],"iteration":444,"passed_time":13.94079949,"remaining_time":1.723020161},
{"learn":[0.2739604246],"iteration":445,"passed_time":13.96771529,"remaining_time":1.691158353},
{"learn":[0.273910676],"iteration":446,"passed_time":13.99139224,"remaining_time":1.65893465},
{"learn":[0.2737693793],"iteration":447,"passed_time":14.02361648,"remaining_time":1.627741198},
{"learn":[0.2735984324],"iteration":448,"passed_time":14.05763447,"remaining_time":1.5967469},
{"learn":[0.2734993667],"iteration":449,"passed_time":14.09134017,"remaining_time":1.565704463},
{"learn":[0.2734651942],"iteration":450,"passed_time":14.12611325,"remaining_time":1.534766184},
{"learn":[0.2733871021],"iteration":451,"passed_time":14.15914883,"remaining_time":1.503626424},
{"learn":[0.2732445182],"iteration":452,"passed_time":14.1932459,"remaining_time":1.472588427},
{"learn":[0.2732054146],"iteration":453,"passed_time":14.22927455,"remaining_time":1.441732663},
{"learn":[0.2731274369],"iteration":454,"passed_time":14.26434265,"remaining_time":1.410759163},
{"learn":[0.2730390902],"iteration":455,"passed_time":14.29697831,"remaining_time":1.379532995},
{"learn":[0.2729691079],"iteration":456,"passed_time":14.32603682,"remaining_time":1.347964077},
{"learn":[0.272896962],"iteration":457,"passed_time":14.35715804,"remaining_time":1.316595278},
{"learn":[0.2728551747],"iteration":458,"passed_time":14.38733693,"remaining_time":1.285143386},
{"learn":[0.2727278131],"iteration":459,"passed_time":14.41648956,"remaining_time":1.253607787},
{"learn":[0.2726766052],"iteration":460,"passed_time":14.44167466,"remaining_time":1.22174688},
{"learn":[0.2726705038],"iteration":461,"passed_time":14.46894576,"remaining_time":1.190086448},
{"learn":[0.2726655356],"iteration":462,"passed_time":14.49603603,"remaining_time":1.158430525},
{"learn":[0.2725607012],"iteration":463,"passed_time":14.52328263,"remaining_time":1.126806411},
{"learn":[0.2724581135],"iteration":464,"passed_time":14.55113242,"remaining_time":1.095246527},
{"learn":[0.2724225244],"iteration":465,"passed_time":14.57661929,"remaining_time":1.063530163},
{"learn":[0.2722779689],"iteration":466,"passed_time":14.60368817,"remaining_time":1.031952269},
{"learn":[0.2721947196],"iteration":467,"passed_time":14.63282198,"remaining_time":1.000534837},
{"learn":[0.2721240667],"iteration":468,"passed_time":14.67472038,"remaining_time":0.9699708566},
{"learn":[0.2720907162],"iteration":469,"passed_time":14.71845507,"remaining_time":0.9394758555},
{"learn":[0.2720170553],"iteration":470,"passed_time":14.74949494,"remaining_time":0.9081430004},
{"learn":[0.2719743487],"iteration":471,"passed_time":14.78420964,"remaining_time":0.8770293852},
{"learn":[0.2719243405],"iteration":472,"passed_time":14.81262685,"remaining_time":0.8455410675},
{"learn":[0.2719002776],"iteration":473,"passed_time":14.84565928,"remaining_time":0.8143188636},
{"learn":[0.2718872433],"iteration":474,"passed_time":14.88272679,"remaining_time":0.7833014099},
{"learn":[0.2716958827],"iteration":475,"passed_time":14.91326473,"remaining_time":0.7519293142},
{"learn":[0.2715050426],"iteration":476,"passed_time":14.95542908,"remaining_time":0.7211213183},
{"learn":[0.2714401954],"iteration":477,"passed_time":14.98969668,"remaining_time":0.6899023576},
{"learn":[0.2713355006],"iteration":478,"passed_time":15.02549329,"remaining_time":0.6587377018},
{"learn":[0.2712922143],"iteration":479,"passed_time":15.06390232,"remaining_time":0.6276625966},
{"learn":[0.2711820078],"iteration":480,"passed_time":15.09947026,"remaining_time":0.5964447711},
{"learn":[0.2710325278],"iteration":481,"passed_time":15.13571475,"remaining_time":0.5652341607},
{"learn":[0.2709237313],"iteration":482,"passed_time":15.17266263,"remaining_time":0.5340274632},
{"learn":[0.2708210794],"iteration":483,"passed_time":15.20125437,"remaining_time":0.5025208055},
{"learn":[0.2707703593],"iteration":484,"passed_time":15.23883999,"remaining_time":0.4713043297},
{"learn":[0.2706362894],"iteration":485,"passed_time":15.27891706,"remaining_time":0.4401334133},
{"learn":[0.2705536497],"iteration":486,"passed_time":15.31754861,"remaining_time":0.4088873345},
{"learn":[0.2704815846],"iteration":487,"passed_time":15.34995291,"remaining_time":0.3774578584},
{"learn":[0.2704328791],"iteration":488,"passed_time":15.38595302,"remaining_time":0.3461052827},
{"learn":[0.2703140451],"iteration":489,"passed_time":15.42188256,"remaining_time":0.3147322972},
{"learn":[0.2702395732],"iteration":490,"passed_time":15.45678027,"remaining_time":0.2833218379},
{"learn":[0.270193855],"iteration":491,"passed_time":15.48502619,"remaining_time":0.2517890438},
{"learn":[0.2700420013],"iteration":492,"passed_time":15.51396957,"remaining_time":0.2202794868},
{"learn":[0.2699994885],"iteration":493,"passed_time":15.54755885,"remaining_time":0.1888367471},
{"learn":[0.2698917822],"iteration":494,"passed_time":15.5777734,"remaining_time":0.1573512465},
{"learn":[0.2698238968],"iteration":495,"passed_time":15.61225326,"remaining_time":0.1259052682},
{"learn":[0.2696665772],"iteration":496,"passed_time":15.64913862,"remaining_time":0.09446160136},
{"learn":[0.2696170651],"iteration":497,"passed_time":15.68189084,"remaining_time":0.06297948129},
{"learn":[0.2695705132],"iteration":498,"passed_time":15.71511274,"remaining_time":0.03149321191},
{"learn":[0.2694461479],"iteration":499,"passed_time":15.75030336,"remaining_time":0}
]}